distkv_ext/inv/__init__.py
distkv_ext/inv/client.py
distkv_ext/inv/config.py
distkv_ext/inv/model.py
distkv_inv-0.22.0.dist-info/METADATA
distkv_inv-0.22.0.dist-info/WHEEL
distkv_inv-0.22.0.dist-info/top_level.txt
distkv_inv-0.22.0.dist-info/zip-safe
distkv_inv-0.22.0.dist-info/RECORD
